mha/__init__.py
mha/ha_device.py
mha/ha_mqtt.py
mha/devices/basic_device.py
mha/devices/binary_sensor.py
mha/devices/light.py
mha/umqtt/__init__.py
mha/utils/constants.py
mha/utils/serializer.py
micropython_home_assistant-0.1.0.dist-info/LICENSE
micropython_home_assistant-0.1.0.dist-info/METADATA
micropython_home_assistant-0.1.0.dist-info/WHEEL
micropython_home_assistant-0.1.0.dist-info/top_level.txt
micropython_home_assistant-0.1.0.dist-info/RECORD
