Metadata-Version: 2.1
Name: micropython-home-assistant
Version: 0.1.0
Summary: Home Assistant MQTT integration for MicroPython
Author-email: lbuque <1102390310@qq.com>
License: MIT
Project-URL: Homepage, https://github.com/lbuque/micropython-home-assistant
Keywords: micropython,home-assistant,MQTT
Classifier: Intended Audience :: Developers
Classifier: Topic :: Software Development :: Libraries
Classifier: Topic :: Software Development :: Embedded Systems
Classifier: Topic :: System :: Hardware
Classifier: License :: OSI Approved :: MIT License
Classifier: Programming Language :: Python :: 3
License-File: LICENSE
